nemi/__init__.py
nemi/workflow.py
nemi_learn-1.0.3.dist-info/LICENSE
nemi_learn-1.0.3.dist-info/METADATA
nemi_learn-1.0.3.dist-info/WHEEL
nemi_learn-1.0.3.dist-info/top_level.txt
nemi_learn-1.0.3.dist-info/RECORD
