Metadata-Version: 2.1
Name: nemi-learn
Version: 1.0.3
Summary: Code to accompany paper
Author-email: Maike Sonnewald <maikes@princeton.edu>
Project-URL: Homepage, https://github.com/maikejulie/NEMI
Project-URL: Bug Tracker, https://github.com/maikejulie/NEMI/issues
Classifier: Programming Language :: Python :: 3
Classifier: Intended Audience :: Science/Research
Requires-Python: >=3.7
License-File: LICENSE
Requires-Dist: umap-learn
Requires-Dist: scikit-learn
Requires-Dist: matplotlib
Requires-Dist: tqdm
Provides-Extra: full
Requires-Dist: pytest ; extra == 'full'
